curses_toolkit/__init__.py
curses_toolkit/actions.py
curses_toolkit/chooser.py
curses_toolkit/core.py
curses_toolkit/list.py
curses_toolkit/menu.py
curses_toolkit/selector.py
curses_toolkit/text.py
tests/__init__.py
tests/conftest.py
tests/test_actions.py
tests/test_chooser.py
tests/test_core.py
tests/test_selector.py
curses_toolkit-1.0.0.dist-info/METADATA
curses_toolkit-1.0.0.dist-info/WHEEL
curses_toolkit-1.0.0.dist-info/top_level.txt
curses_toolkit-1.0.0.dist-info/zip-safe
curses_toolkit-1.0.0.dist-info/RECORD
